docs/.gitignore
docs/Makefile
docs/api.rst
docs/conf.py
docs/data-api.rst
docs/data-download.rst
docs/developer.rst
docs/documenteer.toml
docs/index.rst
docs/installation.rst
docs/introduction.rst
docs/maf-api-batches.rst
docs/maf-api-db.rst
docs/maf-api-maf-contrib.rst
docs/maf-api-maps.rst
docs/maf-api-metricbundles.rst
docs/maf-api-metrics.rst
docs/maf-api-plots.rst
docs/maf-api-run-comparison.rst
docs/maf-api-slicers.rst
docs/maf-api-stackers.rst
docs/maf-api-utils.rst
docs/maf-api.rst
docs/maf.rst
docs/metric_list.py
docs/moving-objects-api.rst
docs/moving-objects.rst
docs/phot-utils-api.rst
docs/phot-utils.rst
docs/prenight.rst
docs/protoarchive.rst
docs/satellite-constellations-api.rst
docs/satellite-constellations.rst
docs/selfcal-api.rst
docs/selfcal.rst
docs/sim-archive-api.rst
docs/skybrightness-api.rst
docs/skybrightness.rst
docs/user-guide.rst
docs/vseqarchive-architecture.rst
docs/vseqarchive-setup.rst
docs/vseqarchive.rst
rubin_sim/__init__.py
rubin_sim/data/__init__.py
rubin_sim/data/rs_download_data.py
rubin_sim/maf/__init__.py
rubin_sim/maf/ddf_dir.py
rubin_sim/maf/generate_ss.py
rubin_sim/maf/glance_dir.py
rubin_sim/maf/maf_night_report.py
rubin_sim/maf/make_fbs_tracking_db.py
rubin_sim/maf/metadata_dir.py
rubin_sim/maf/run_moving_calc.py
rubin_sim/maf/run_moving_fractions.py
rubin_sim/maf/run_moving_join.py
rubin_sim/maf/run_selfcal_metric.py
rubin_sim/maf/scimaf_dir.py
rubin_sim/maf/show_maf.py
rubin_sim/maf/batches/__init__.py
rubin_sim/maf/batches/altaz_batch.py
rubin_sim/maf/batches/col_map_dict.py
rubin_sim/maf/batches/common.py
rubin_sim/maf/batches/ddf_batch.py
rubin_sim/maf/batches/filterchange_batch.py
rubin_sim/maf/batches/glance_batch.py
rubin_sim/maf/batches/hourglass_batch.py
rubin_sim/maf/batches/info_batch.py
rubin_sim/maf/batches/metadata_batch.py
rubin_sim/maf/batches/moving_objects_batch.py
rubin_sim/maf/batches/openshutter_batch.py
rubin_sim/maf/batches/radar_limited.py
rubin_sim/maf/batches/science_radar_batch.py
rubin_sim-2.6.1.dist-info/licenses/LICENSE
rubin_sim-2.6.1.dist-info/METADATA
rubin_sim-2.6.1.dist-info/WHEEL
rubin_sim-2.6.1.dist-info/entry_points.txt
rubin_sim-2.6.1.dist-info/top_level.txt
rubin_sim-2.6.1.dist-info/RECORD
