Metadata-Version: 2.4
Name: rubin-sim
Version: 2.6.1
Summary: Scheduler, survey strategy analysis, and other simulation tools for Rubin Observatory.
License: GPL
Project-URL: documentation, https://rubin-sim.lsst.io
Project-URL: repository, https://github.com/lsst/rubin_sim
Classifier: Intended Audience :: Science/Research
Classifier: Operating System :: OS Independent
Classifier: Programming Language :: Python :: 3
Classifier: Programming Language :: Python :: 3.11
Classifier: Programming Language :: Python :: 3.12
Classifier: Programming Language :: Python :: 3.13
Classifier: Topic :: Scientific/Engineering :: Astronomy
License-File: LICENSE
Requires-Dist: astroplan
Requires-Dist: astropy
Requires-Dist: colorcet
Requires-Dist: cycler
Requires-Dist: gitpython
Requires-Dist: h5py
Requires-Dist: healpy
Requires-Dist: matplotlib
Requires-Dist: numexpr
Requires-Dist: numpy
Requires-Dist: pandas
Requires-Dist: pyarrow
Requires-Dist: rubin-scheduler>=3.18
Requires-Dist: scikit-learn
Requires-Dist: scipy
Requires-Dist: shapely
Requires-Dist: skyfield>=1.52
Requires-Dist: skyproj
Requires-Dist: sqlalchemy
Requires-Dist: tables
Requires-Dist: tqdm
Provides-Extra: test
Requires-Dist: pytest; extra == "test"
Requires-Dist: black>=25; extra == "test"
Requires-Dist: ruff; extra == "test"
Requires-Dist: isort; extra == "test"
Requires-Dist: pytest-cov; extra == "test"
Requires-Dist: testing.postgresql; extra == "test"
Provides-Extra: dev
Requires-Dist: documenteer[guide]; extra == "dev"
Provides-Extra: extras
Requires-Dist: george; extra == "extras"
Requires-Dist: pyoorb; extra == "extras"
Provides-Extra: vseqarchive
Requires-Dist: click; extra == "vseqarchive"
Requires-Dist: psycopg2; extra == "vseqarchive"
Requires-Dist: botocore; extra == "vseqarchive"
Requires-Dist: boto3; extra == "vseqarchive"
Dynamic: license-file
